deeplp/__init__.py
deeplp/main.py
deeplp/models.py
deeplp/ode.py
deeplp/problems.py
deeplp/solvers.py
deeplp/train.py
deeplp/utils.py
deeplp-0.7.1.dist-info/entry_points.txt
deeplp-0.7.1.dist-info/METADATA
deeplp-0.7.1.dist-info/WHEEL
deeplp-0.7.1.dist-info/RECORD
