Metadata-Version: 2.3
Name: deeplp
Version: 0.7.1
Summary: A package that solves Linear Programs using pytorch
Author: Mohammed Alshahrani
Author-email: mmogib@gmail.com
Requires-Python: >=3.10
Classifier: Programming Language :: Python :: 3
Classifier: Programming Language :: Python :: 3.10
Classifier: Programming Language :: Python :: 3.11
Classifier: Programming Language :: Python :: 3.12
Classifier: Programming Language :: Python :: 3.13
Requires-Dist: colorama (>=0.4.6,<0.5.0)
Requires-Dist: matplotlib (>=3.10.1,<4.0.0)
Requires-Dist: numpy (>=2.2.3,<3.0.0)
Requires-Dist: prettytable (>=3.15.1,<4.0.0)
Requires-Dist: pulp (>=3.0.2,<4.0.0)
Requires-Dist: tqdm (>=4.67.1,<5.0.0)
